Metadata-Version: 2.1
Name: blobfile-gdb-fork
Version: 0.17.3
Summary: Read GCS and local paths with the same interface, clone of tensorflow.io.gfile
Home-page: https://github.com/christopher-hesse/blobfile
Author: Christopher Hesse
License: Public Domain
Platform: UNKNOWN
Requires-Python: >=3.7.0
Provides-Extra: dev
